zope.errorview-2.1-py3.12-nspkg.pth
zope/errorview/__init__.py
zope/errorview/browser.py
zope/errorview/browser.zcml
zope/errorview/http.py
zope/errorview/http.zcml
zope/errorview/interfaces.py
zope/errorview/i18n/__init__.py
zope/errorview/i18n/locales/zope.errorview.pot
zope/errorview/i18n/locales/en/LC_MESSAGES/zope.errorview.po
zope/errorview/i18n/locales/nl/LC_MESSAGES/zope.errorview.po
zope/errorview/tests/__init__.py
zope/errorview/tests/ftesting.zcml
zope/errorview/tests/test_browser.py
zope/errorview/tests/test_event.py
zope/errorview/tests/test_http.py
zope_errorview-2.1.dist-info/LICENSE.rst
zope_errorview-2.1.dist-info/METADATA
zope_errorview-2.1.dist-info/WHEEL
zope_errorview-2.1.dist-info/namespace_packages.txt
zope_errorview-2.1.dist-info/top_level.txt
zope_errorview-2.1.dist-info/RECORD
